django_persistent_message-1.3.3.dist-info/licenses/LICENSE
persistent_message/VERSION
persistent_message/__init__.py
persistent_message/decorators.py
persistent_message/models.py
persistent_message/urls.py
persistent_message/fixtures/test.json
persistent_message/migrations/0001_initial.py
persistent_message/migrations/0002_auto_20220421_2356.py
persistent_message/migrations/__init__.py
persistent_message/static/persistent_message/css/vendor/bootstrap-datetimepicker.min.css
persistent_message/static/persistent_message/js/main.js
persistent_message/static/persistent_message/js/vendor/bootstrap-datetimepicker.min.js
persistent_message/templates/access_denied.html
persistent_message/templates/manage.html
persistent_message/templates/manage_wrapper.html
persistent_message/tests/__init__.py
persistent_message/tests/test_api.py
persistent_message/tests/test_models.py
persistent_message/views/__init__.py
persistent_message/views/api.py
django_persistent_message-1.3.3.dist-info/METADATA
django_persistent_message-1.3.3.dist-info/WHEEL
django_persistent_message-1.3.3.dist-info/top_level.txt
django_persistent_message-1.3.3.dist-info/RECORD
