Metadata-Version: 2.4
Name: Django-Persistent-Message
Version: 1.3.3
Summary: Django-Persistent-Message
Home-page: https://github.com/uw-it-aca/django-persistent-message
Author: UW-IT Student & Educational Technology Services
Author-email: aca-it@uw.edu
License: Apache License, Version 2.0
Classifier: Intended Audience :: Developers
Classifier: License :: OSI Approved :: Apache Software License
Classifier: Operating System :: OS Independent
Classifier: Programming Language :: Python
License-File: LICENSE
Requires-Dist: Django
Requires-Dist: python-dateutil
Requires-Dist: nh3
Dynamic: author
Dynamic: author-email
Dynamic: classifier
Dynamic: description
Dynamic: home-page
Dynamic: license
Dynamic: license-file
Dynamic: requires-dist
Dynamic: summary
